r2d7py/__init__.py
r2d7py/r2d7.py
r2d7py/r2d7py.py
r2d7py/test.py
r2d7py-0.0.7.dist-info/LICENSE
r2d7py-0.0.7.dist-info/METADATA
r2d7py-0.0.7.dist-info/WHEEL
r2d7py-0.0.7.dist-info/top_level.txt
r2d7py-0.0.7.dist-info/RECORD
