Metadata-Version: 2.1
Name: r2d7py
Version: 0.0.7
Summary: R2D7 shade controller over Ethernet
Home-page: https://github.com/dubnom/r2d7py
Author: Michael Dubno
Author-email: michael@dubno.com
License: UNKNOWN
Platform: UNKNOWN
Classifier: Programming Language :: Python :: 3
Classifier: License :: OSI Approved :: MIT License
Classifier: Operating System :: OS Independent
